README.md
setup.py
psearcherr/BaiduEngine.py
psearcherr/BaseEngine.py
psearcherr/BingEngine.py
psearcherr/__init__.py
psearcherr.egg-info/PKG-INFO
psearcherr.egg-info/SOURCES.txt
psearcherr.egg-info/dependency_links.txt
psearcherr.egg-info/requires.txt
psearcherr.egg-info/top_level.txt