Metadata-Version: 2.1
Name: psearcherr
Version: 0.1.1
Summary: Rewrite for Python baidu search client: iridesc/psearcher
Home-page: https://github.com/duangsuse-valid-projects/psearcher-r
Author: duangsuse
Author-email: fedora-opensuse@outlook.com
License: MIT
Platform: UNKNOWN
Classifier: Programming Language :: Python :: 3
Classifier: License :: OSI Approved :: MIT License
Classifier: Operating System :: OS Independent
